immutable_time_travel.py
setup.py
immutable_time_travel.egg-info/PKG-INFO
immutable_time_travel.egg-info/SOURCES.txt
immutable_time_travel.egg-info/dependency_links.txt
immutable_time_travel.egg-info/top_level.txt